p9813.py
setup.py
micropython_p9813.egg-info/PKG-INFO
micropython_p9813.egg-info/SOURCES.txt
micropython_p9813.egg-info/dependency_links.txt
micropython_p9813.egg-info/top_level.txt